InstaUserInfo/__init__.py
InstaUserInfo/instauserinfo.py
InstaUserInfo/test.py
instauserinfo-0.0.1.dist-info/LICENSE
instauserinfo-0.0.1.dist-info/METADATA
instauserinfo-0.0.1.dist-info/WHEEL
instauserinfo-0.0.1.dist-info/top_level.txt
instauserinfo-0.0.1.dist-info/RECORD
