Metadata-Version: 2.1
Name: instauserinfo
Version: 0.0.1
Summary: Get Instagram user info
Home-page: UNKNOWN
Author: SamuraiCoder
Author-email: <aelboutaheri@gmail.com>
License: UNKNOWN
Keywords: python,instagram,requests
Platform: UNKNOWN
Classifier: Development Status :: 1 - Planning
Classifier: Intended Audience :: Developers
Classifier: Programming Language :: Python :: 3
Classifier: Operating System :: Unix
Classifier: Operating System :: MacOS :: MacOS X
Classifier: Operating System :: Microsoft :: Windows
License-File: LICENSE
Requires-Dist: requests
